tilly_sitemap/__init__.py
tilly_sitemap/main.py
tilly_sitemap-0.0.6.dist-info/LICENSE
tilly_sitemap-0.0.6.dist-info/METADATA
tilly_sitemap-0.0.6.dist-info/WHEEL
tilly_sitemap-0.0.6.dist-info/entry_points.txt
tilly_sitemap-0.0.6.dist-info/top_level.txt
tilly_sitemap-0.0.6.dist-info/RECORD
