Metadata-Version: 2.2
Name: tilly-sitemap
Version: 0.0.6
Summary: Tilly plugin creating a sitemap.xml
Home-page: https://github.com/tilly-pub/tilly-sitemap
Author: Ronald Luitwieler
Author-email: ronald.luitwieler@gmail.com
Classifier: Programming Language :: Python :: 3
Classifier: License :: OSI Approved :: MIT License
Classifier: Operating System :: OS Independent
Requires-Python: >=3.9
License-File: LICENSE
Requires-Dist: tilly>=0.0.10
Dynamic: author
Dynamic: author-email
Dynamic: classifier
Dynamic: description
Dynamic: description-content-type
Dynamic: home-page
Dynamic: requires-dist
Dynamic: requires-python
Dynamic: summary
